xlsx_provider/VERSION
xlsx_provider/__init__.py
xlsx_provider/commons.py
xlsx_provider/loader.py
xlsx_provider/example_dags/__init__.py
xlsx_provider/example_dags/sample_xlsx_to_parquet.py
xlsx_provider/operators/__init__.py
xlsx_provider/operators/from_xlsx_operator.py
xlsx_provider/operators/from_xlsx_query_operator.py
xlsx_provider/operators/to_xlsx_operator.py
airflow_provider_xlsx-1.0.1.dist-info/LICENSE
airflow_provider_xlsx-1.0.1.dist-info/METADATA
airflow_provider_xlsx-1.0.1.dist-info/WHEEL
airflow_provider_xlsx-1.0.1.dist-info/entry_points.txt
airflow_provider_xlsx-1.0.1.dist-info/top_level.txt
airflow_provider_xlsx-1.0.1.dist-info/RECORD
