Metadata-Version: 2.1
Name: airflow-provider-xlsx
Version: 1.0.1
Summary: Airflow operators for reading and writing XLSX files
Home-page: https://github.com/andreax79/airflow-provider-xlsx
Author: Andrea Bonomi
Author-email: andrea.bonomi@gmail.com
License: Apache License, Version 2.0
Platform: UNKNOWN
Classifier: Operating System :: OS Independent
Classifier: Programming Language :: Python
Classifier: Topic :: Software Development :: Libraries :: Python Modules
Classifier: Programming Language :: Python :: 3
Classifier: Programming Language :: Python :: 3.4
Classifier: Programming Language :: Python :: 3.5
Classifier: Programming Language :: Python :: 3.6
Classifier: Programming Language :: Python :: 3.7
Classifier: Programming Language :: Python :: 3.8
Classifier: Programming Language :: Python :: 3.9
Requires-Python: >=3.4
License-File: LICENSE
Requires-Dist: apache-airflow (>=2.0)
Requires-Dist: openpyxl
Requires-Dist: pyarrow
Requires-Dist: xlrd
